st2client/BUILD
st2client/__init__.py
st2client/base.py
st2client/client.py
st2client/config.py
st2client/config_parser.py
st2client/shell.py
st2client/commands/BUILD
st2client/commands/__init__.py
st2client/commands/action.py
st2client/commands/action_alias.py
st2client/commands/auth.py
st2client/commands/inquiry.py
st2client/commands/keyvalue.py
st2client/commands/noop.py
st2client/commands/pack.py
st2client/commands/policy.py
st2client/commands/rbac.py
st2client/commands/resource.py
st2client/commands/rule.py
st2client/commands/rule_enforcement.py
st2client/commands/sensor.py
st2client/commands/service_registry.py
st2client/commands/timer.py
st2client/commands/trace.py
st2client/commands/trigger.py
st2client/commands/triggerinstance.py
st2client/commands/webhook.py
st2client/commands/workflow.py
st2client/exceptions/BUILD
st2client/exceptions/__init__.py
st2client/exceptions/base.py
st2client/exceptions/operations.py
st2client/formatters/BUILD
st2client/formatters/__init__.py
st2client/formatters/doc.py
st2client/formatters/execution.py
st2client/formatters/table.py
st2client/models/BUILD
st2client/models/__init__.py
st2client/models/action.py
st2client/models/action_alias.py
st2client/models/aliasexecution.py
st2client/models/auth.py
st2client/models/config.py
st2client/models/core.py
st2client/models/inquiry.py
st2client/models/keyvalue.py
st2client/models/pack.py
st2client/models/policy.py
st2client/models/rbac.py
st2client/models/reactor.py
st2client/models/service_registry.py
st2client/models/timer.py
st2client/models/trace.py
st2client/models/webhook.py
st2client/utils/BUILD
st2client/utils/__init__.py
st2client/utils/color.py
st2client/utils/date.py
st2client/utils/httpclient.py
st2client/utils/interactive.py
st2client/utils/jsutil.py
st2client/utils/logging.py
st2client/utils/misc.py
st2client/utils/profiler.py
st2client/utils/schema.py
st2client/utils/strutil.py
st2client/utils/terminal.py
st2client/utils/types.py
tests/fixtures/__init__.py
st2client_gcx-3.8.1.1.dist-info/LICENSE
st2client_gcx-3.8.1.1.dist-info/METADATA
st2client_gcx-3.8.1.1.dist-info/WHEEL
st2client_gcx-3.8.1.1.dist-info/entry_points.txt
st2client_gcx-3.8.1.1.dist-info/top_level.txt
st2client_gcx-3.8.1.1.dist-info/RECORD
