Metadata-Version: 2.1
Name: st2client-gcx
Version: 3.8.1.1
Summary: Python client library and CLI for the StackStorm (st2) event-driven automation platform.
Home-page: https://stackstorm.com/
Author: StackStorm
Author-email: info@stackstorm.com
License: UNKNOWN
Project-URL: Pack Exchange, https://exchange.stackstorm.org
Project-URL: Repository, https://github.com/StackStorm/st2
Project-URL: Documentation, https://docs.stackstorm.com
Project-URL: Community, https://stackstorm.com/community-signup
Project-URL: Questions, https://github.com/StackStorm/st2/discussions
Project-URL: Donate, https://funding.communitybridge.org/projects/stackstorm
Project-URL: News/Blog, https://stackstorm.com/blog
Project-URL: Security, https://docs.stackstorm.com/latest/security.html
Project-URL: Bug Reports, https://github.com/StackStorm/st2/issues
Platform: UNKNOWN
Classifier: Development Status :: 5 - Production/Stable
Classifier: Intended Audience :: Information Technology
Classifier: Intended Audience :: Developers
Classifier: Intended Audience :: System Administrators
Classifier: License :: OSI Approved :: Apache Software License
Classifier: Operating System :: POSIX :: Linux
Classifier: Programming Language :: Python
Classifier: Programming Language :: Python :: 3
Classifier: Programming Language :: Python :: 3.6
Requires-Dist: argcomplete ==1.12.3
Requires-Dist: cffi <1.15.0
Requires-Dist: chardet <3.1.0
Requires-Dist: cryptography ==39.0.1
Requires-Dist: importlib-metadata <=4.10.1,>=4.8.3
Requires-Dist: jsonpath-rw ==1.4.0
Requires-Dist: jsonschema ==2.6.0
Requires-Dist: orjson ==3.5.2
Requires-Dist: prettytable ==2.1.0
Requires-Dist: prompt-toolkit ==1.0.15
Requires-Dist: pyOpenSSL ==23.1.0
Requires-Dist: pysocks
Requires-Dist: python-dateutil ==2.8.1
Requires-Dist: python-editor ==1.0.4
Requires-Dist: pytz ==2021.1
Requires-Dist: pyyaml ==6.0.1
Requires-Dist: requests[security] ==2.25.1
Requires-Dist: six ==1.13.0
Requires-Dist: sseclient-py ==1.7
Requires-Dist: typing-extensions <4.2
Requires-Dist: zipp <3.16.0
